{"target": "https://www.ncbi.nlm.nih.gov/research/pubtator-api/publications/export/biocjson?pmids=30139987", "sourcedb": "PubMed", "sourceid": "30139987", "text": "DNAJC12-associated developmental delay, movement disorder, and mild hyperphenylalaninemia identified by whole-exome sequencing re-analysis. Hyperphenylalaninemia, movement disorder, and intellectual disability due to variants in DNAJC12 is a recently reported inherited neurotransmitter disorder. We report two new patients with this new genetic disorder. Patient 1 is a 6-year-11-month-old boy with mild hyperphenylalaninemia and global developmental delay (GDD). Seventeen-year-old male sibling of patient 1 had GDD from the first year of life. He had mild hyperphenylalaninemia at 11.5 years of age following his younger brother's diagnosis. He had low levels of homovanillic acid and 5-hydroxyindolacetic acid in the cerebrospinal fluid. Whole-exome sequencing (WES) was normal in 2016. After the first description of DNAJC12-associated hyperphenylalaninemia, dystonia, and intellectual disability in 2017, WES re-analysis identified a homozygous c.58_59delGG (p.(Gly20Metfs*2)) variant in DNAJC12. His younger brother was homozygous for the same variant, confirming the diagnosis of DNAJC12-associated hyperphenylalaninemia, movement disorder, and intellectual disability. Mild hyperphenylalaninemia and GDD should warrant targeted DNAJC12 genetic testing for the early diagnosis of DNAJC12-associated hyperphenylalaninemia, movement disorder, and intellectual disability.", "project": "Standigm_training", "denotations": [{"id": "T1", "span": {"begin": 40, "end": 57}, "obj": "DISEASE"}, {"id": "T10", "span": {"begin": 459, "end": 462}, "obj": "DISEASE"}, {"id": "T11", "span": {"begin": 514, "end": 517}, "obj": "DISEASE"}, {"id": "T12", "span": {"begin": 559, "end": 580}, "obj": "DISEASE"}, {"id": "T13", "span": {"begin": 652, "end": 655}, "obj": "NEGREG"}, {"id": "T14", "span": {"begin": 656, "end": 662}, "obj": "MPA"}, {"id": "T15", "span": {"begin": 666, "end": 683}, "obj": "MPA"}, {"id": "T17", "span": {"begin": 864, "end": 872}, "obj": "DISEASE"}, {"id": "T18", "span": {"begin": 878, "end": 901}, "obj": "DISEASE"}, {"id": "T19", "span": {"begin": 927, "end": 937}, "obj": "REG"}, {"id": "T2", "span": {"begin": 68, "end": 89}, "obj": "DISEASE"}, {"id": "T20", "span": {"begin": 951, "end": 963}, "obj": "VAR"}, {"id": "T21", "span": {"begin": 983, "end": 990}, "obj": "VAR"}, {"id": "T22", "span": {"begin": 994, "end": 1001}, "obj": "GENE"}, {"id": "T23", "span": {"begin": 1051, "end": 1058}, "obj": "VAR"}, {"id": "T25", "span": {"begin": 1130, "end": 1147}, "obj": "DISEASE"}, {"id": "T26", "span": {"begin": 1153, "end": 1176}, "obj": "DISEASE"}, {"id": "T27", "span": {"begin": 1183, "end": 1204}, "obj": "DISEASE"}, {"id": "T28", "span": {"begin": 1209, "end": 1212}, "obj": "DISEASE"}, {"id": "T3", "span": {"begin": 140, "end": 161}, "obj": "DISEASE"}, {"id": "T30", "span": {"begin": 1330, "end": 1347}, "obj": "DISEASE"}, {"id": "T31", "span": {"begin": 1353, "end": 1376}, "obj": "DISEASE"}, {"id": "T4", "span": {"begin": 163, "end": 180}, "obj": "DISEASE"}, {"id": "T5", "span": {"begin": 186, "end": 209}, "obj": "DISEASE"}, {"id": "T6", "span": {"begin": 217, "end": 225}, "obj": "VAR"}, {"id": "T7", "span": {"begin": 229, "end": 236}, "obj": "GENE"}, {"id": "T8", "span": {"begin": 405, "end": 426}, "obj": "DISEASE"}, {"id": "T9", "span": {"begin": 431, "end": 457}, "obj": "DISEASE"}, {"id": "T32", "span": {"begin": 0, "end": 38}, "obj": "DISEASE"}, {"id": "T33", "span": {"begin": 822, "end": 862}, "obj": "DISEASE"}, {"id": "T34", "span": {"begin": 1088, "end": 1128}, "obj": "DISEASE"}, {"id": "T35", "span": {"begin": 1237, "end": 1244}, "obj": "GENE"}, {"id": "T36", "span": {"begin": 1288, "end": 1328}, "obj": "DISEASE"}, {"id": "T37", "span": {"begin": 210, "end": 216}, "obj": "REG"}, {"id": "T38", "span": {"begin": 688, "end": 713}, "obj": "MPA"}, {"id": "T39", "span": {"begin": 1060, "end": 1070}, "obj": "REG"}], "relations": [{"id": "R0", "pred": "ThemeOf", "subj": "T7", "obj": "T6"}, {"id": "R1", "pred": "ThemeOf", "subj": "T14", "obj": "T13"}, {"id": "R2", "pred": "ThemeOf", "subj": "T15", "obj": "T14"}, {"id": "R3", "pred": "ThemeOf", "subj": "T20", "obj": "T19"}, {"id": "R4", "pred": "ThemeOf", "subj": "T21", "obj": "T19"}, {"id": "R5", "pred": "ThemeOf", "subj": "T22", "obj": "T20"}, {"id": "R6", "pred": "ThemeOf", "subj": "T22", "obj": "T21"}, {"id": "R8", "pred": "ThemeOf", "subj": "T6", "obj": "T37"}, {"id": "R9", "pred": "ThemeOf", "subj": "T3", "obj": "T37"}, {"id": "R10", "pred": "ThemeOf", "subj": "T4", "obj": "T37"}, {"id": "R11", "pred": "ThemeOf", "subj": "T5", "obj": "T37"}, {"id": "R12", "pred": "ThemeOf", "subj": "T38", "obj": "T14"}, {"id": "R13", "pred": "ThemeOf", "subj": "T34", "obj": "T39"}, {"id": "R14", "pred": "ThemeOf", "subj": "T25", "obj": "T39"}, {"id": "R15", "pred": "ThemeOf", "subj": "T26", "obj": "T39"}, {"id": "R16", "pred": "ThemeOf", "subj": "T23", "obj": "T39"}, {"id": "R17", "pred": "ThemeOf", "subj": "T22", "obj": "T23"}, {"id": "R18", "pred": "ThemeOf", "subj": "T18", "obj": "T19"}, {"id": "R19", "pred": "ThemeOf", "subj": "T17", "obj": "T19"}, {"id": "R20", "pred": "ThemeOf", "subj": "T33", "obj": "T19"}], "attributes": [], "modifications": [], "config": {"entity types": [{"id": "DISEASE", "default": true}, {"id": "NEGREG"}, {"id": "MPA"}, {"id": "REG"}, {"id": "VAR"}, {"id": "GENE"}], "relation types": [{"id": "ThemeOf", "default": true}, {"id": "CauseOf"}]}}