{"target": "https://www.ncbi.nlm.nih.gov/research/pubtator-api/publications/export/biocjson?pmids=31604653", "sourcedb": "PubMed", "sourceid": "31604653", "text": "'Amish Nemaline Myopathy' in 2 Italian siblings harbouring a novel homozygous mutation in Troponin-I gene. Amish Nemaline Myopathy is a severe form of nemaline myopathy associated to mutation in TNNT1 gene, firstly reported among the Old Order Amish. Here we report two Italian siblings who manifested, by the age of 7 months, progressive and severe muscle weakness and wasting, respiratory insufficiency, pectus carinatum deformity and failure to thrive. Muscle biopsy was consistent with nemaline myopathy and novel homozygous missense mutation in TNNT1 was found. Our cases expand the mutational spectrum of TNNT1, confirm the invariable peculiar clinical phenotype also outside the Amish population, and suggest that TNNT1 should be considered for molecular analysis in NM patients with chest deformities and progressive contractures.", "project": "Standigm_training", "denotations": [{"id": "T0", "span": {"begin": 7, "end": 24}, "obj": "DISEASE"}, {"id": "T1", "span": {"begin": 48, "end": 58}, "obj": "REG"}, {"id": "T10", "span": {"begin": 291, "end": 301}, "obj": "REG"}, {"id": "T13", "span": {"begin": 437, "end": 444}, "obj": "NEGREG"}, {"id": "T14", "span": {"begin": 448, "end": 454}, "obj": "CPA"}, {"id": "T15", "span": {"begin": 490, "end": 507}, "obj": "DISEASE"}, {"id": "T16", "span": {"begin": 529, "end": 546}, "obj": "VAR"}, {"id": "T17", "span": {"begin": 550, "end": 555}, "obj": "GENE"}, {"id": "T18", "span": {"begin": 611, "end": 616}, "obj": "GENE"}, {"id": "T19", "span": {"begin": 721, "end": 726}, "obj": "GENE"}, {"id": "T2", "span": {"begin": 78, "end": 86}, "obj": "VAR"}, {"id": "T3", "span": {"begin": 90, "end": 100}, "obj": "GENE"}, {"id": "T4", "span": {"begin": 113, "end": 130}, "obj": "DISEASE"}, {"id": "T5", "span": {"begin": 151, "end": 168}, "obj": "DISEASE"}, {"id": "T6", "span": {"begin": 169, "end": 179}, "obj": "REG"}, {"id": "T7", "span": {"begin": 183, "end": 191}, "obj": "VAR"}, {"id": "T8", "span": {"begin": 195, "end": 200}, "obj": "GENE"}, {"id": "T9", "span": {"begin": 215, "end": 223}, "obj": "REG"}, {"id": "T22", "span": {"begin": 379, "end": 404}, "obj": "MPA"}, {"id": "T23", "span": {"begin": 406, "end": 432}, "obj": "MPA"}, {"id": "T24", "span": {"begin": 350, "end": 377}, "obj": "MPA"}, {"id": "T25", "span": {"begin": 774, "end": 776}, "obj": "DISEASE"}], "relations": [{"id": "R0", "pred": "ThemeOf", "subj": "T0", "obj": "T1"}, {"id": "R1", "pred": "ThemeOf", "subj": "T2", "obj": "T1"}, {"id": "R11", "pred": "ThemeOf", "subj": "T16", "obj": "T13"}, {"id": "R12", "pred": "ThemeOf", "subj": "T17", "obj": "T16"}, {"id": "R2", "pred": "ThemeOf", "subj": "T3", "obj": "T2"}, {"id": "R3", "pred": "ThemeOf", "subj": "T4", "obj": "T6"}, {"id": "R4", "pred": "ThemeOf", "subj": "T5", "obj": "T6"}, {"id": "R5", "pred": "ThemeOf", "subj": "T7", "obj": "T6"}, {"id": "R6", "pred": "ThemeOf", "subj": "T7", "obj": "T9"}, {"id": "R7", "pred": "ThemeOf", "subj": "T7", "obj": "T10"}, {"id": "R8", "pred": "ThemeOf", "subj": "T8", "obj": "T7"}, {"id": "R9", "pred": "ThemeOf", "subj": "T14", "obj": "T13"}, {"id": "R13", "pred": "ThemeOf", "subj": "T16", "obj": "T24"}, {"id": "R14", "pred": "ThemeOf", "subj": "T16", "obj": "T22"}, {"id": "R15", "pred": "ThemeOf", "subj": "T16", "obj": "T23"}, {"id": "R16", "pred": "ThemeOf", "subj": "T25", "obj": "T5"}, {"id": "R17", "pred": "ThemeOf", "subj": "T25", "obj": "T15"}], "attributes": [], "modifications": [], "config": {"entity types": [{"id": "MPA", "color": "#77dddd"}, {"id": "DISEASE", "default": true}, {"id": "REG"}, {"id": "NEGREG"}, {"id": "CPA"}, {"id": "VAR"}, {"id": "GENE"}], "relation types": [{"id": "ThemeOf", "default": true}, {"id": "CauseOf"}]}}