{"target": "https://www.ncbi.nlm.nih.gov/research/pubtator-api/publications/export/biocjson?pmids=30969155", "sourceid": "30969155", "text": "Placental Pathology in Down Syndrome-Associated Transient Abnormal Myelopoiesis. Transient abnormal myelopoiesis is a hematopoietic disorder that occurs in up to 10% of neonates with Down syndrome. It is characterized by leukocytosis and the presence of circulating blast cells harboring truncating GATA1 mutations with variable multiorgan system involvement. Placental involvement of transient abnormal myelopoiesis is infrequently described. Placental examination and identifying features related to transient abnormal myelopoiesis could be one of the early, if not the only, means of diagnosis of this condition in affected stillbirths, premature infants, and a subset of asymptomatic neonates. This article provides an overview of the placental pathology in transient abnormal myelopoiesis with review of the literature, and also discusses the important differential diagnoses.", "project": "Pseudo-labled dataset", "denotations": [{"id": "T-0", "span": {"begin": 23, "end": 47}, "obj": "DISEASE"}, {"id": "T-1", "span": {"begin": 28, "end": 47}, "obj": "REG"}, {"id": "T-2", "span": {"begin": 48, "end": 79}, "obj": "DISEASE"}, {"id": "T-3", "span": {"begin": 81, "end": 112}, "obj": "DISEASE"}, {"id": "T-4", "span": {"begin": 146, "end": 152}, "obj": "REG"}, {"id": "T-5", "span": {"begin": 183, "end": 196}, "obj": "DISEASE"}, {"id": "T-6", "span": {"begin": 204, "end": 217}, "obj": "REG"}, {"id": "T-7", "span": {"begin": 242, "end": 250}, "obj": "REG"}, {"id": "T-8", "span": {"begin": 288, "end": 298}, "obj": "VAR"}, {"id": "T-9", "span": {"begin": 299, "end": 304}, "obj": "GENE"}, {"id": "T-10", "span": {"begin": 305, "end": 314}, "obj": "VAR"}, {"id": "T-11", "span": {"begin": 329, "end": 358}, "obj": "CPA"}, {"id": "T-12", "span": {"begin": 385, "end": 416}, "obj": "DISEASE"}, {"id": "T-13", "span": {"begin": 502, "end": 533}, "obj": "DISEASE"}, {"id": "T-14", "span": {"begin": 762, "end": 793}, "obj": "DISEASE"}], "relations": [{"id": "R-0", "pred": "ThemeOf", "subj": "T-0", "obj": "T-1"}, {"id": "R-1", "pred": "ThemeOf", "subj": "T-2", "obj": "T-1"}, {"id": "R-2", "pred": "ThemeOf", "subj": "T-3", "obj": "T-4"}, {"id": "R-3", "pred": "ThemeOf", "subj": "T-3", "obj": "T-6"}, {"id": "R-4", "pred": "ThemeOf", "subj": "T-5", "obj": "T-4"}, {"id": "R-5", "pred": "ThemeOf", "subj": "T-6", "obj": "T-7"}, {"id": "R-6", "pred": "ThemeOf", "subj": "T-8", "obj": "T-7"}, {"id": "R-7", "pred": "ThemeOf", "subj": "T-10", "obj": "T-8"}, {"id": "R-8", "pred": "ThemeOf", "subj": "T-9", "obj": "T-10"}]}